.gitignore
CHANGES.rst
LICENSE.txt
README.rst
distribute_setup.py
fabfile.py
setup.py
chitwanabm/__init__.py
chitwanabm/agents.py
chitwanabm/chitwanabmrc.windows
chitwanabm/initialize.py
chitwanabm/modelloop.py
chitwanabm/process_scenario.py
chitwanabm/rcparams.default
chitwanabm/runmodel.py
chitwanabm/statistics.py
chitwanabm/test.py
chitwanabm/threaded_batch_run.py
chitwanabm.egg-info/PKG-INFO
chitwanabm.egg-info/SOURCES.txt
chitwanabm.egg-info/dependency_links.txt
chitwanabm.egg-info/entry_points.txt
chitwanabm.egg-info/requires.txt
chitwanabm.egg-info/top_level.txt
chitwanabm.egg-info/zip-safe
chitwanabm/R/batch_calculations.R
chitwanabm/R/batch_plots.R
chitwanabm/R/batch_process.R
chitwanabm/R/batch_process.bat
chitwanabm/R/calc_NBH_stats.R
chitwanabm/R/data_preprocess.R
chitwanabm/R/install_dependencies.R
chitwanabm/R/person_data_analysis.R
chitwanabm/R/plot_LULC.R
chitwanabm/R/plot_baseline_versus_observed.R
chitwanabm/R/plot_events.R
chitwanabm/R/plot_pop.R
chitwanabm/R/plot_psns_data.R
chitwanabm/R/plot_scenario_results.R
doc/Makefile
doc/analysis.rst
doc/chitwanabm.rst
doc/conf.py
doc/index.rst
doc/make.bat
doc/references.rst
doc/running.rst
doc/setup.rst