Metadata-Version: 1.1
Name: chitwanabm
Version: 1.5
Summary: An agent-based model of the Chitwan Valley, Nepal
Home-page: http://rohan.sdsu.edu/~zvoleff/research/chitwanabm
Author: Alex Zvoleff
Author-email: azvoleff@mail.sdsu.edu
License: GPL v3 or later
Keywords: agent-based modeling ABM simulation model
Platform: UNKNOWN
Classifier: Development Status :: 4 - Beta
Classifier: Natural Language :: English
Classifier: Topic :: Software Development
Classifier: Topic :: Scientific/Engineering
Classifier: Topic :: Scientific/Engineering :: Artificial Life
Classifier: Intended Audience :: Science/Research
Classifier: License :: OSI Approved :: GNU General Public License v3 or later (GPLv3+)
Classifier: Operating System :: OS Independent
Classifier: Programming Language :: Python
Classifier: Programming Language :: Python :: 2.7
